tinyPub/__init__.py
tinyPub/__main__.py
tinyPub/addnotation.py
tinyPub/navParser.py
tinyPub/htmlParser/__init__.py
tinyPub/htmlParser/default.py
tinyPub/htmlParser/renderer.py
tinyPub/htmlParser/styles.py
tinyPub/htmlParser/textFormater.py
tinypub_HakierGrzonzo-2.0.2.dist-info/LICENSE.md
tinypub_HakierGrzonzo-2.0.2.dist-info/METADATA
tinypub_HakierGrzonzo-2.0.2.dist-info/WHEEL
tinypub_HakierGrzonzo-2.0.2.dist-info/entry_points.txt
tinypub_HakierGrzonzo-2.0.2.dist-info/top_level.txt
tinypub_HakierGrzonzo-2.0.2.dist-info/RECORD
