Metadata-Version: 2.1
Name: tinypub-HakierGrzonzo
Version: 2.0.2
Summary: A console based epub ebook reader.
Home-page: https://github.com/HakierGrzonzo/tinyPub
Author: Grzegorz Koperwas
Author-email: Grzegorz.Koperwas.dev@gmail.com
License: UNKNOWN
Platform: UNKNOWN
Classifier: Programming Language :: Python :: 3
Classifier: License :: OSI Approved :: MIT License
Classifier: Operating System :: POSIX :: Linux
Classifier: Development Status :: 4 - Beta
Classifier: Intended Audience :: End Users/Desktop
Requires-Python: >=3.6.1
